<?xml version="1.0" encoding="UTF-8"?>
<!DOCTYPE mapper PUBLIC "-//mybatis.org//DTD Mapper 3.0//EN" "http://mybatis.org/dtd/mybatis-3-mapper.dtd">
<mapper namespace="com.qubaolai.mapper.DepartmentMapper">
  <resultMap id="BaseResultMap" type="com.qubaolai.po.Department">
    <!--
      WARNING - @mbg.generated
      This element is automatically generated by MyBatis Generator, do not modify.
      This element was generated on Tue Oct 29 15:10:59 CST 2019.
    -->
    <id column="id" jdbcType="VARCHAR" property="id" />
    <result column="department_number" jdbcType="INTEGER" property="departmentNumber" />
    <result column="name" jdbcType="VARCHAR" property="name" />
    <result column="manager" jdbcType="VARCHAR" property="manager" />
    <result column="telephone" jdbcType="VARCHAR" property="telephone" />
    <result column="address" jdbcType="VARCHAR" property="address" />
    <result column="notes" jdbcType="VARCHAR" property="notes" />
  </resultMap>
  <sql id="Example_Where_Clause">
    <!--
      WARNING - @mbg.generated
      This element is automatically generated by MyBatis Generator, do not modify.
      This element was generated on Tue Oct 29 15:10:59 CST 2019.
    -->
    <where>
      <foreach collection="oredCriteria" item="criteria" separator="or">
        <if test="criteria.valid">
          <trim prefix="(" prefixOverrides="and" suffix=")">
            <foreach collection="criteria.criteria" item="criterion">
              <choose>
                <when test="criterion.noValue">
                  and ${criterion.condition}
                </when>
                <when test="criterion.singleValue">
                  and ${criterion.condition} #{criterion.value}
                </when>
                <when test="criterion.betweenValue">
                  and ${criterion.condition} #{criterion.value} and #{criterion.secondValue}
                </when>
                <when test="criterion.listValue">
                  and ${criterion.condition}
                  <foreach close=")" collection="criterion.value" item="listItem" open="(" separator=",">
                    #{listItem}
                  </foreach>
                </when>
              </choose>
            </foreach>
          </trim>
        </if>
      </foreach>
    </where>
  </sql>
  <sql id="Update_By_Example_Where_Clause">
    <!--
      WARNING - @mbg.generated
      This element is automatically generated by MyBatis Generator, do not modify.
      This element was generated on Tue Oct 29 15:10:59 CST 2019.
    -->
    <where>
      <foreach collection="example.oredCriteria" item="criteria" separator="or">
        <if test="criteria.valid">
          <trim prefix="(" prefixOverrides="and" suffix=")">
            <foreach collection="criteria.criteria" item="criterion">
              <choose>
                <when test="criterion.noValue">
                  and ${criterion.condition}
                </when>
                <when test="criterion.singleValue">
                  and ${criterion.condition} #{criterion.value}
                </when>
                <when test="criterion.betweenValue">
                  and ${criterion.condition} #{criterion.value} and #{criterion.secondValue}
                </when>
                <when test="criterion.listValue">
                  and ${criterion.condition}
                  <foreach close=")" collection="criterion.value" item="listItem" open="(" separator=",">
                    #{listItem}
                  </foreach>
                </when>
              </choose>
            </foreach>
          </trim>
        </if>
      </foreach>
    </where>
  </sql>
  <sql id="Base_Column_List">
    <!--
      WARNING - @mbg.generated
      This element is automatically generated by MyBatis Generator, do not modify.
      This element was generated on Tue Oct 29 15:10:59 CST 2019.
    -->
    id, department_number, name, manager, telephone, address, notes
  </sql>
  <select id="selectByExample" parameterType="com.qubaolai.po.DepartmentExample" resultMap="BaseResultMap">
    <!--
      WARNING - @mbg.generated
      This element is automatically generated by MyBatis Generator, do not modify.
      This element was generated on Tue Oct 29 15:10:59 CST 2019.
    -->
    select
    <if test="distinct">
      distinct
    </if>
    <include refid="Base_Column_List" />
    from department
    <if test="_parameter != null">
      <include refid="Example_Where_Clause" />
    </if>
    <if test="orderByClause != null">
      order by ${orderByClause}
    </if>
  </select>
  <select id="selectByPrimaryKey" parameterType="java.lang.String" resultMap="BaseResultMap">
    <!--
      WARNING - @mbg.generated
      This element is automatically generated by MyBatis Generator, do not modify.
      This element was generated on Tue Oct 29 15:10:59 CST 2019.
    -->
    select 
    <include refid="Base_Column_List" />
    from department
    where id = #{id,jdbcType=VARCHAR}
  </select>
  <delete id="deleteByPrimaryKey" parameterType="java.lang.String">
    <!--
      WARNING - @mbg.generated
      This element is automatically generated by MyBatis Generator, do not modify.
      This element was generated on Tue Oct 29 15:10:59 CST 2019.
    -->
    delete from department
    where id = #{id,jdbcType=VARCHAR}
  </delete>
  <delete id="deleteByExample" parameterType="com.qubaolai.po.DepartmentExample">
    <!--
      WARNING - @mbg.generated
      This element is automatically generated by MyBatis Generator, do not modify.
      This element was generated on Tue Oct 29 15:10:59 CST 2019.
    -->
    delete from department
    <if test="_parameter != null">
      <include refid="Example_Where_Clause" />
    </if>
  </delete>
  <insert id="insert" parameterType="com.qubaolai.po.Department">
    <!--
      WARNING - @mbg.generated
      This element is automatically generated by MyBatis Generator, do not modify.
      This element was generated on Tue Oct 29 15:10:59 CST 2019.
    -->
    insert into department (id, department_number, name, 
      manager, telephone, address, 
      notes)
    values (#{id,jdbcType=VARCHAR}, #{departmentNumber,jdbcType=INTEGER}, #{name,jdbcType=VARCHAR}, 
      #{manager,jdbcType=VARCHAR}, #{telephone,jdbcType=VARCHAR}, #{address,jdbcType=VARCHAR}, 
      #{notes,jdbcType=VARCHAR})
  </insert>
  <insert id="insertSelective" parameterType="com.qubaolai.po.Department">
    <!--
      WARNING - @mbg.generated
      This element is automatically generated by MyBatis Generator, do not modify.
      This element was generated on Tue Oct 29 15:10:59 CST 2019.
    -->
    insert into department
    <trim prefix="(" suffix=")" suffixOverrides=",">
      <if test="id != null">
        id,
      </if>
      <if test="departmentNumber != null">
        department_number,
      </if>
      <if test="name != null">
        name,
      </if>
      <if test="manager != null">
        manager,
      </if>
      <if test="telephone != null">
        telephone,
      </if>
      <if test="address != null">
        address,
      </if>
      <if test="notes != null">
        notes,
      </if>
    </trim>
    <trim prefix="values (" suffix=")" suffixOverrides=",">
      <if test="id != null">
        #{id,jdbcType=VARCHAR},
      </if>
      <if test="departmentNumber != null">
        #{departmentNumber,jdbcType=INTEGER},
      </if>
      <if test="name != null">
        #{name,jdbcType=VARCHAR},
      </if>
      <if test="manager != null">
        #{manager,jdbcType=VARCHAR},
      </if>
      <if test="telephone != null">
        #{telephone,jdbcType=VARCHAR},
      </if>
      <if test="address != null">
        #{address,jdbcType=VARCHAR},
      </if>
      <if test="notes != null">
        #{notes,jdbcType=VARCHAR},
      </if>
    </trim>
  </insert>
  <select id="countByExample" parameterType="com.qubaolai.po.DepartmentExample" resultType="java.lang.Long">
    <!--
      WARNING - @mbg.generated
      This element is automatically generated by MyBatis Generator, do not modify.
      This element was generated on Tue Oct 29 15:10:59 CST 2019.
    -->
    select count(*) from department
    <if test="_parameter != null">
      <include refid="Example_Where_Clause" />
    </if>
  </select>
  <update id="updateByExampleSelective" parameterType="map">
    <!--
      WARNING - @mbg.generated
      This element is automatically generated by MyBatis Generator, do not modify.
      This element was generated on Tue Oct 29 15:10:59 CST 2019.
    -->
    update department
    <set>
      <if test="record.id != null">
        id = #{record.id,jdbcType=VARCHAR},
      </if>
      <if test="record.departmentNumber != null">
        department_number = #{record.departmentNumber,jdbcType=INTEGER},
      </if>
      <if test="record.name != null">
        name = #{record.name,jdbcType=VARCHAR},
      </if>
      <if test="record.manager != null">
        manager = #{record.manager,jdbcType=VARCHAR},
      </if>
      <if test="record.telephone != null">
        telephone = #{record.telephone,jdbcType=VARCHAR},
      </if>
      <if test="record.address != null">
        address = #{record.address,jdbcType=VARCHAR},
      </if>
      <if test="record.notes != null">
        notes = #{record.notes,jdbcType=VARCHAR},
      </if>
    </set>
    <if test="_parameter != null">
      <include refid="Update_By_Example_Where_Clause" />
    </if>
  </update>
  <update id="updateByExample" parameterType="map">
    <!--
      WARNING - @mbg.generated
      This element is automatically generated by MyBatis Generator, do not modify.
      This element was generated on Tue Oct 29 15:10:59 CST 2019.
    -->
    update department
    set id = #{record.id,jdbcType=VARCHAR},
      department_number = #{record.departmentNumber,jdbcType=INTEGER},
      name = #{record.name,jdbcType=VARCHAR},
      manager = #{record.manager,jdbcType=VARCHAR},
      telephone = #{record.telephone,jdbcType=VARCHAR},
      address = #{record.address,jdbcType=VARCHAR},
      notes = #{record.notes,jdbcType=VARCHAR}
    <if test="_parameter != null">
      <include refid="Update_By_Example_Where_Clause" />
    </if>
  </update>
  <update id="updateByPrimaryKeySelective" parameterType="com.qubaolai.po.Department">
    <!--
      WARNING - @mbg.generated
      This element is automatically generated by MyBatis Generator, do not modify.
      This element was generated on Tue Oct 29 15:10:59 CST 2019.
    -->
    update department
    <set>
      <if test="departmentNumber != null">
        department_number = #{departmentNumber,jdbcType=INTEGER},
      </if>
      <if test="name != null">
        name = #{name,jdbcType=VARCHAR},
      </if>
      <if test="manager != null">
        manager = #{manager,jdbcType=VARCHAR},
      </if>
      <if test="telephone != null">
        telephone = #{telephone,jdbcType=VARCHAR},
      </if>
      <if test="address != null">
        address = #{address,jdbcType=VARCHAR},
      </if>
      <if test="notes != null">
        notes = #{notes,jdbcType=VARCHAR},
      </if>
    </set>
    where id = #{id,jdbcType=VARCHAR}
  </update>
  <update id="updateByPrimaryKey" parameterType="com.qubaolai.po.Department">
    <!--
      WARNING - @mbg.generated
      This element is automatically generated by MyBatis Generator, do not modify.
      This element was generated on Tue Oct 29 15:10:59 CST 2019.
    -->
    update department
    set department_number = #{departmentNumber,jdbcType=INTEGER},
      name = #{name,jdbcType=VARCHAR},
      manager = #{manager,jdbcType=VARCHAR},
      telephone = #{telephone,jdbcType=VARCHAR},
      address = #{address,jdbcType=VARCHAR},
      notes = #{notes,jdbcType=VARCHAR}
    where id = #{id,jdbcType=VARCHAR}
  </update>
</mapper>